oboparser.py
setup.py
similarity.py
similarity_inter.py
similarity_intra.py
neuroner.egg-info/PKG-INFO
neuroner.egg-info/SOURCES.txt
neuroner.egg-info/dependency_links.txt
neuroner.egg-info/top_level.txt