Metadata-Version: 1.1
Name: neuroner
Version: 0.0.3
Summary: named entity recognition for neurons
Home-page: https://github.com/renaud/neuroNER
Author: Renaud Richardet, Shreejoy Tripathy
Author-email: renaud@apache.org, stripathy@chibi.ubc.ca
License: Apache License (2.0)
Keywords: neuroscience
Platform: UNKNOWN
Classifier: Development Status :: 3 - Alpha
Classifier: Intended Audience :: Developers
Classifier: License :: OSI Approved :: Apache Software License
Classifier: Programming Language :: Python :: 2.7
Classifier: Operating System :: OS Independent
Classifier: Environment :: Console
